unifi_api_client/__init__.py
unifi_api_client/api_client.py
unifi_api_client/exceptions.py
unifi_api_client/http_client.py
unifi_api_client/resources/__init__.py
unifi_api_client/resources/devices.py
unifi_api_client/resources/hosts.py
unifi_api_client/resources/isp_metrics.py
unifi_api_client/resources/resources.py
unifi_api_client/resources/sites.py
unifi_api_client-1.0.0a4.dist-info/LICENSE
unifi_api_client-1.0.0a4.dist-info/METADATA
unifi_api_client-1.0.0a4.dist-info/WHEEL
unifi_api_client-1.0.0a4.dist-info/RECORD
