Metadata-Version: 2.1
Name: unifi-api-client
Version: 1.0.0a4
Summary: 
Author: David Thomas
Author-email: techguydave@protonmail.com
Requires-Python: >=3.10,<4.0
Classifier: Programming Language :: Python :: 3
Classifier: Programming Language :: Python :: 3.10
Classifier: Programming Language :: Python :: 3.11
Classifier: Programming Language :: Python :: 3.12
Classifier: Programming Language :: Python :: 3.13
Requires-Dist: requests (>=2.32.3,<3.0.0)
Requires-Dist: tenacity (>=9.0.0,<10.0.0)
